README.md
setup.py
akstatistic/__init__.py
akstatistic/akstatistic.py
akstatistic.egg-info/PKG-INFO
akstatistic.egg-info/SOURCES.txt
akstatistic.egg-info/dependency_links.txt
akstatistic.egg-info/top_level.txt