Metadata-Version: 2.1
Name: akstatistic
Version: 0.0.2
Summary: Project Code Statistic
Home-page: https://gitee.com/aktools/akstatistic.git
Author: Kuture
Author-email: kuture@163.com
License: MIT Licence
Keywords: pip,akstatistic,aktools,kuture,statistic
Platform: any
Requires-Python: >=3
